BarkNotificator/__init__.py
BarkNotificator/barknotificator.py
BarkNotificator/exception.py
BarkNotificator/key.p8
barknotificator_fixed-0.1.3.dist-info/licenses/LICENSE
barknotificator_fixed-0.1.3.dist-info/METADATA
barknotificator_fixed-0.1.3.dist-info/WHEEL
barknotificator_fixed-0.1.3.dist-info/top_level.txt
barknotificator_fixed-0.1.3.dist-info/RECORD
