Metadata-Version: 2.4
Name: barknotificator-fixed
Version: 0.1.3
Summary: A package that allows you to send notifications to your iOS device using the Bark app without self server
Author: funny-cat-happy
Author-email: tigerhowl@qq.com
Keywords: bark,notification,iOS,barknotificator
Classifier: Development Status :: 3 - Alpha
Classifier: Intended Audience :: Developers
Classifier: Programming Language :: Python :: 3
Classifier: Operating System :: MacOS :: MacOS X
Classifier: Operating System :: Microsoft :: Windows
Classifier: Operating System :: POSIX :: Linux
Classifier: License :: OSI Approved :: GNU General Public License v3 (GPLv3)
Requires-Python: >=3
License-File: LICENSE
Requires-Dist: httpx[http2]
Requires-Dist: pyjwt
Requires-Dist: cryptography
Dynamic: author
Dynamic: author-email
Dynamic: classifier
Dynamic: description
Dynamic: description-content-type
Dynamic: keywords
Dynamic: license-file
Dynamic: requires-dist
Dynamic: requires-python
Dynamic: summary
